Flaskapp/__init__.py
Flaskapp/cli.py
flask_interface-0.1.dist-info/METADATA
flask_interface-0.1.dist-info/WHEEL
flask_interface-0.1.dist-info/entry_points.txt
flask_interface-0.1.dist-info/top_level.txt
flask_interface-0.1.dist-info/RECORD
