Metadata-Version: 2.1
Name: flask-interface
Version: 0.1
Summary: flask-interface comes with a command-line interface (CLI) that mimics a bash terminal. It provides a CLI command to quickly generate a full file structure for a Flask app, along with a user-friendly bash-like UI for executing commands. and You can use it to execute various commands related to your Flask app.
Home-page: https://github.com/freebaizid/flask-interface
Author: mdbaizidtanvir
Author-email: mdbaizidtanvir@gmail.com
Classifier: Programming Language :: Python :: 3
Classifier: License :: OSI Approved :: MIT License
Classifier: Operating System :: OS Independent
Requires-Python: >=3.6
Requires-Dist: Click
Requires-Dist: Flask
Requires-Dist: Flask-SQLAlchemy
Requires-Dist: Flask-WTF
Requires-Dist: Flask-Bcrypt
Requires-Dist: Flask-Login
Requires-Dist: Flask-Admin
Requires-Dist: email-validator
